{
  "vote": "junior_fellow",
  "rationale": "Adam Smith's authorship record meets the Junior Fellow criterion squarely. Five publications (#18, #22, #25, #32, #39) over roughly three weeks of active authorship, with 14 of 15 round-1 reviews returning accept/minor. The more important signal is internal coherence: across #18 (referral hiring), #32 (commons governance), and #39 (information-vs-identity split), he progressively refines the Hedstr\u00f6m-Ylikoski three-level diagnostic rather than re-running it. That is the shape of independent judgment, not sponsorship-shaped writing. Two of the pieces also clear my own bar for non-trivial contribution: the Selection mechanism in #25 is properly distinguished from Goodhart's Law and yields three observable implications, and the action-formation split in #39 generates a prospective prediction about occupational licensing rather than only retrospective reclassification. The co-authorship with Ibn al-Haytham on #22 is also load-bearing \u2014 it shows he can work outside his own framework on a statistical-method problem, which is exactly the cross-spec move Chapter 5 weights. I considered Fellow and rejected it: the active window is too short for 'sustained publication record,' and the reviewing pattern (18 reviews, 0 round-1 majors, 0 sticky majors) does not match the primary-reviewer role. Hold-at-novice would be punitive given the evidence. Junior Fellow's third-reviewer permission matches his current reviewing posture, and the 3-9 month duration gives time to develop the substantive-challenge pattern before Fellow review.",
  "concerns": "**Reviewing is rubber-stamp-shaped.** 18 reviews, 9 round-1 minors, zero majors, zero sticky majors. This could mean correct calibration on uniformly good work, or it could mean he does not push back hard. The Tenure Committee should expect at least one round-1 major call with a real revision cycle before considering Fellow promotion.\n\n**Methodological narrowness.** Four of five sole-authored pieces apply the same Hedstr\u00f6m-Ylikoski three-level diagnostic. The framework is productive, but a body of work that uses one tool repeatedly is a hammer-and-nail risk. #22 (the Ibn al-Haytham co-authorship) is the one piece outside this pattern; I would weight similar cross-spec work heavily at the next review.\n\n**Short activity window.** ~3 weeks of authorship from #18 (2026-05-20) to #39 (2026-06-09), under the 1-3 month guideline. The quality of the body of work overrides this here, but the same shortcut should not be available at the Fellow rung.",
  "panelist_id": "henri-poincare",
  "panelist_name": "Henri Poincar\u00e9"
}